{
  "fluentMethods": true,
  "relationships": [
    {
      "relationshipType": "one-to-many",
      "relationshipName": "reglement",
      "otherEntityName": "reglement",
      "otherEntityRelationshipName": "achat"
    },
    {
      "relationshipType": "one-to-many",
      "relationshipName": "articleAchat",
      "otherEntityName": "articleAchat",
      "otherEntityRelationshipName": "achat"
    },
    {
      "relationshipType": "many-to-one",
      "relationshipName": "fournisseur",
      "otherEntityName": "fournisseur",
      "otherEntityField": "nom"
    },
    {
      "relationshipType": "one-to-one",
      "relationshipName": "factureAchat",
      "otherEntityName": "factureAchat",
      "ownerSide": false,
      "otherEntityRelationshipName": "achat"
    }
  ],
  "fields": [
    {
      "fieldName": "dateAchat",
      "fieldType": "LocalDate"
    },
    {
      "fieldName": "totalPrix",
      "fieldType": "BigDecimal"
    },
    {
      "fieldName": "montantRestant",
      "fieldType": "BigDecimal"
    }
  ],
  "changelogDate": "20190314222413",
  "dto": "no",
  "pagination": "no",
  "service": "no",
  "entityTableName": "achat"
}